texts/__init__.py
texts-0.1.dist-info/METADATA
texts-0.1.dist-info/WHEEL
texts-0.1.dist-info/top_level.txt
texts-0.1.dist-info/RECORD
