Metadata-Version: 1.0
Name: texts
Version: 0.1
Summary: Lesson on OOP through linguistics.
Home-page: http://github.com/infosmith/texts
Author: infosmith
Author-email: davidsmith@kenzie.academy
License: proprietary
Platform: UNKNOWN
